{
  "_fv": 69,
  "_type": "recipe",
  "definition": {
    "recipeType": "Smithing",
    "recipeRetstackSize": 1,
    "group": "",
    "cookingBookCategory": "MISC",
    "xpReward": 0.0,
    "cookingTime": 200,
    "craftingBookCategory": "MISC",
    "recipeShapeless": false,
    "smithingInputStack": {
      "value": "Items.AMETHYST_SHARD"
    },
    "smithingInputAdditionStack": {
      "value": "Items.DYE#14"
    },
    "smithingReturnStack": {
      "value": "CUSTOM:CrystalOrange"
    },
    "name": "crystal_recipe_orange",
    "namespace": "mod"
  }
}