{
  "_fv": 39,
  "_type": "livingentity",
  "definition": {
    "mobName": "Penguin",
    "mobLabel": "",
    "mobModelName": "Modelpenguin",
    "mobModelTexture": "penguin.png",
    "mobModelGlowTexture": "",
    "modelWidth": 0.8,
    "modelHeight": 0.9,
    "modelShadowSize": 0.7000000000000001,
    "mountedYOffset": 0.0,
    "hasSpawnEgg": false,
    "spawnEggBaseColor": {
      "value": -1,
      "falpha": 0.0
    },
    "spawnEggDotColor": {
      "value": -16777165,
      "falpha": 0.0
    },
    "creativeTab": {
      "value": "CUSTOM:Crtab"
    },
    "isBoss": false,
    "bossBarColor": "PINK",
    "bossBarType": "PROGRESS",
    "equipmentMainHand": {
      "value": ""
    },
    "equipmentOffHand": {
      "value": ""
    },
    "equipmentHelmet": {
      "value": ""
    },
    "equipmentBody": {
      "value": ""
    },
    "equipmentLeggings": {
      "value": ""
    },
    "equipmentBoots": {
      "value": ""
    },
    "mobBehaviourType": "Creature",
    "mobCreatureType": "UNDEFINED",
    "attackStrength": 3,
    "attackKnockback": 0.0,
    "knockbackResistance": 0.0,
    "movementSpeed": 0.25,
    "armorBaseValue": 1.0,
    "trackingRange": 64,
    "followRange": 16,
    "health": 20,
    "xpAmount": 0,
    "waterMob": false,
    "flyingMob": false,
    "guiBoundTo": "<NONE>",
    "inventorySize": 9,
    "inventoryStackSize": 64,
    "disableCollisions": false,
    "ridable": false,
    "canControlForward": false,
    "canControlStrafe": false,
    "immuneToFire": false,
    "immuneToArrows": false,
    "immuneToFallDamage": true,
    "immuneToCactus": false,
    "immuneToDrowning": true,
    "immuneToLightning": false,
    "immuneToPotions": false,
    "immuneToPlayer": false,
    "immuneToExplosion": false,
    "immuneToTrident": false,
    "immuneToAnvil": false,
    "immuneToWither": false,
    "immuneToDragonBreath": false,
    "mobDrop": {
      "value": "Items.FISH#1"
    },
    "livingSound": {
      "value": "CUSTOM:mob.penguin"
    },
    "hurtSound": {
      "value": "CUSTOM:mob.penguin"
    },
    "deathSound": {
      "value": "entity.generic.death"
    },
    "stepSound": {
      "value": ""
    },
    "hasAI": true,
    "aiBase": "(none)",
    "aixml": "<xml xmlns=\"https://developers.google.com/blockly/xml\"><block type=\"aitasks_container\" deletable=\"false\" x=\"40\" y=\"40\"><next><block type=\"attack_action\"><field name=\"callhelp\">TRUE</field><field name=\"condition\">PenguinGunther,null</field><next><block type=\"attack_on_collide\"><field name=\"speed\">1.2</field><field name=\"longmemory\">TRUE</field><field name=\"condition\">PenguinGunther,null</field><next><block type=\"attack_entity\"><field name=\"insight\">TRUE</field><field name=\"nearby\">FALSE</field><field name=\"entity\">CUSTOM:Nootnoot</field><field name=\"condition\">PenguinGunther,PenguinGunther</field><next><block type=\"leap_at_target\"><field name=\"speed\">0.5</field><field name=\"condition\">null,null</field><next><block type=\"wander\"><field name=\"speed\">0.7</field><field name=\"condition\">null,null</field><next><block type=\"follow_entity\"><field name=\"speed\">0.8</field><field name=\"maxrange\">3</field><field name=\"followarea\">3</field><field name=\"condition\">null,null</field><next><block type=\"swim_in_water\"><field name=\"condition\">PenguinFloat,PenguinFloat</field><next><block type=\"look_around\"><field name=\"condition\">null,null</field><next><block type=\"swim\"><field name=\"speed\">1</field><field name=\"condition\">PenguinSwim,PenguinSwim</field></block></next></block></next></block></next></block></next></block></next></block></next></block></next></block></next></block></next></block></xml>",
    "breedable": false,
    "tameable": false,
    "breedTriggerItems": [],
    "ranged": false,
    "rangedAttackItem": {
      "value": ""
    },
    "rangedItemType": "Default item",
    "rangedAttackInterval": 20,
    "rangedAttackRadius": 10.0,
    "spawnThisMob": false,
    "doesDespawnWhenIdle": true,
    "spawningProbability": 12,
    "mobSpawningType": "creature",
    "minNumberOfMobsPerGroup": 1,
    "maxNumberOfMobsPerGroup": 10,
    "restrictionBiomes": [
      {
        "value": "deep_frozen_ocean"
      },
      {
        "value": "frozen_ocean"
      },
      {
        "value": "frozen_peaks"
      },
      {
        "value": "mutated_ice_flats"
      },
      {
        "value": "cold_beach"
      },
      {
        "value": "snowy_tundra"
      },
      {
        "value": "taiga_cold"
      }
    ],
    "spawnInDungeons": false
  }
}